Metadata-Version: 2.4
Name: yolo4r
Version: 1.1.13
Summary: Streamlined, modular, multi-source YOLO training & detection pipeline for research.
Author: Kyle S. Goertler - Trevelline Lab
License: MIT
Requires-Python: >=3.3
Requires-Dist: torch>=2.8.0
Requires-Dist: torchvision>=0.23.0
Requires-Dist: numpy>=1.23.0
Requires-Dist: opencv-python-headless>=4.7.0
Requires-Dist: Pillow>=10.0.1
Requires-Dist: matplotlib>=3.6.3
Requires-Dist: pandas>=1.5.3
Requires-Dist: pyyaml>=6.0.0
Requires-Dist: tqdm>=4.64.1
Requires-Dist: ultralytics==8.3.184
Requires-Dist: ultralytics-thop>=2.0.16
Requires-Dist: wandb>=0.21.1
Requires-Dist: psutil>=5.9.5
Requires-Dist: seaborn>=0.13.0
Requires-Dist: shapely
